bg4h/__init__.py
bg4h/bg_docas.py
bg4h/bg_flowges.py
bg4h/bg_main.py
bg4h/bg_soc.py
bg4h/helpers.py
bg4h-1.0.48.dist-info/licenses/LICENSE
bg4h-1.0.48.dist-info/METADATA
bg4h-1.0.48.dist-info/WHEEL
bg4h-1.0.48.dist-info/top_level.txt
bg4h-1.0.48.dist-info/RECORD
