Metadata-Version: 2.4
Name: bg4h
Version: 1.0.48
Summary: bg table definitions for humans
Author-email: "ct.galega" <soporte@ctgalega.com>
Classifier: Programming Language :: Python :: 3
Classifier: License :: OSI Approved :: MIT License
Classifier: Operating System :: OS Independent
Requires-Python: >=3.8
License-File: LICENSE
Dynamic: license-file
